home/__init__.py
home/admin.py
home/apps.py
home/models.py
home/tests.py
home/urls.py
home/views.py
home/migrations/__init__.py
cheap_local_websites_home-0.0.1.dist-info/LICENSE
cheap_local_websites_home-0.0.1.dist-info/METADATA
cheap_local_websites_home-0.0.1.dist-info/WHEEL
cheap_local_websites_home-0.0.1.dist-info/top_level.txt
cheap_local_websites_home-0.0.1.dist-info/RECORD
