Metadata-Version: 2.1
Name: cheap-local-websites-home
Version: 0.0.1
Summary: A Web App to display basic static pages
Home-page: https://www.cheaplocalwebsites.com
Author: John
Author-email: john@cheaplocalwebsites.com
License: UNKNOWN
Platform: UNKNOWN
Classifier: Programming Language :: Python :: 3
Classifier: License :: OSI Approved :: MIT License
Classifier: Operating System :: OS Independent
Requires-Python: >=3.6
